molml/__init__.py
molml/Data/__init__.py
molml/Data/Chembl/__init__.py
molml/Data/Data_prep/__init__.py
molml/Data/example_data/CHEMBL2047_EC50.csv
molml/Data/example_data/__init__.py
molml/Datastructures/__init__.py
molml/Datastructures/dataset.py
molml/Datastructures/molecule.py
molml/Representations/__init__.py
molml/Representations/descriptors.py
molml/Representations/graphs.py
molml/Representations/strings.py
molml/Tools/__init__.py
molml/Tools/cluster.py
molml/Tools/metrics.py
molml/Tools/optimize.py
molml/Tools/parsing.py
molml/Tools/splitting.py
molml/Tools/utils.py
molml/Viz/__init__.py
molml/Viz/multivariate.py
molml_tools-1.0.12.dist-info/LICENSE
molml_tools-1.0.12.dist-info/METADATA
molml_tools-1.0.12.dist-info/WHEEL
molml_tools-1.0.12.dist-info/top_level.txt
molml_tools-1.0.12.dist-info/RECORD
