Metadata-Version: 2.1
Name: molml-tools
Version: 1.0.12
Summary: A collection of tools for molecular machine learning
Home-page: https://github.com/derekvantilborg/molmlkit
Author: Derek van Tilborg
Author-email: d.w.v.tilborg@tue.nl
License: MIT
Platform: UNKNOWN
License-File: LICENSE
Requires-Dist: tqdm
Requires-Dist: requests
Requires-Dist: twine
Requires-Dist: importlib-metadata
Requires-Dist: pandas
Requires-Dist: numpy
Requires-Dist: matplotlib
Requires-Dist: seaborn
Requires-Dist: chembl-webresource-client
Requires-Dist: scikit-learn
Requires-Dist: scikit-optimize
Requires-Dist: rdkit-pypi
Requires-Dist: keras
